readability_transformers/ReadNet.py
readability_transformers/ReadabilityTransformer.py
readability_transformers/__init__.py
readability_transformers/file_utils.py
readability_transformers/reset_cache.py
readability_transformers/dataset/CEFRDataset.py
readability_transformers/dataset/CommonLitDataset.py
readability_transformers/dataset/Dataset.py
readability_transformers/dataset/__init__.py
readability_transformers/features/DocumentLingFeat.py
readability_transformers/features/FeatureBase.py
readability_transformers/features/LingFeat.py
readability_transformers/features/SentenceLingFeat.py
readability_transformers/features/TRUNAJOD.py
readability_transformers/features/TransformersLogits.py
readability_transformers/features/__init__.py
readability_transformers/features/lf/__init__.py
readability_transformers/features/lf/extractor.py
readability_transformers/features/lf/utils.py
readability_transformers/features/lf/AdvancedSemantic/CKKF.py
readability_transformers/features/lf/AdvancedSemantic/OSKF.py
readability_transformers/features/lf/AdvancedSemantic/WBKF.py
readability_transformers/features/lf/AdvancedSemantic/WoKF.py
readability_transformers/features/lf/AdvancedSemantic/__init__.py
readability_transformers/features/lf/AdvancedSemantic/model/.expElogbeta.npy
readability_transformers/features/lf/AdvancedSemantic/model/.id2word
readability_transformers/features/lf/AdvancedSemantic/model/.state
readability_transformers/features/lf/AdvancedSemantic/model/cokec100
readability_transformers/features/lf/AdvancedSemantic/model/cokec100.expElogbeta.npy
readability_transformers/features/lf/AdvancedSemantic/model/cokec100.id2word
readability_transformers/features/lf/AdvancedSemantic/model/cokec100.state
readability_transformers/features/lf/AdvancedSemantic/model/cokec150
readability_transformers/features/lf/AdvancedSemantic/model/cokec150.expElogbeta.npy
readability_transformers/features/lf/AdvancedSemantic/model/cokec150.id2word
readability_transformers-0.3.1.dist-info/LICENSE
readability_transformers-0.3.1.dist-info/METADATA
readability_transformers-0.3.1.dist-info/WHEEL
readability_transformers-0.3.1.dist-info/top_level.txt
readability_transformers-0.3.1.dist-info/RECORD
